bayesmab/__init__.py
bayesmab/bandit.py
bayesmab-1.0.0.dist-info/licenses/LICENSE
bayesmab-1.0.0.dist-info/METADATA
bayesmab-1.0.0.dist-info/WHEEL
bayesmab-1.0.0.dist-info/top_level.txt
bayesmab-1.0.0.dist-info/RECORD
